{
  "main": [
    {
      "name": "Home",
      "url": "/"
    },
    {
      "name": "About",
      "url": "/about"
    },
    {
      "name": "Newsletter",
      "url": "https://built-by-daryl.kit.com/fd9773952f"
    },
    {
      "name": "More",
      "url": "",
      "hasChildren": true,
      "children": [
        {
          "name": "Privacy Policy",
          "url": "/privacy-policy"
        }
      ]
    }
  ],
  "footer": [
    {
      "name": "Newsletter",
      "url": "https://built-by-daryl.kit.com/fd9773952f"
    },
    {
      "name": "Privacy Policy",
      "url": "/privacy-policy"
    }
  ]
}
